python_code_guardian/__init__.py
python_code_guardian/__main__.py
python_code_guardian/cli.py
python_code_guardian/reporter.py
python_code_guardian/server.py
python_code_guardian/checkers/__init__.py
python_code_guardian/checkers/base_checker.py
python_code_guardian/checkers/complexity_checker.py
python_code_guardian/checkers/coverage_checker.py
python_code_guardian/checkers/duplicate_checker.py
python_code_guardian/checkers/lint_checker.py
python_code_guardian/checkers/structure_checker.py
python_code_guardian/checkers/typo_checker.py
python_code_guardian/config/__init__.py
python_code_guardian/config/config_loader.py
python_code_guardian/utils/__init__.py
python_code_guardian/utils/checker_factory.py
python_code_guardian/utils/git_utils.py
python_code_guardian_mcp-0.1.0.dist-info/licenses/LICENSE
python_code_guardian_mcp-0.1.0.dist-info/METADATA
python_code_guardian_mcp-0.1.0.dist-info/WHEEL
python_code_guardian_mcp-0.1.0.dist-info/entry_points.txt
python_code_guardian_mcp-0.1.0.dist-info/top_level.txt
python_code_guardian_mcp-0.1.0.dist-info/RECORD
