Metadata-Version: 2.4
Name: python-code-guardian-mcp
Version: 0.1.0
Summary: Python code quality guardian - automated linting, complexity analysis, and code health monitoring via MCP
Author: Priyanshi Jajoo
License: MIT
Project-URL: Homepage, https://github.com/priyanshi9692/py-sage-mcp
Project-URL: Documentation, https://github.com/priyanshi9692/py-sage-mcp/blob/main/README.md
Project-URL: Repository, https://github.com/priyanshi9692/py-sage-mcp.git
Keywords: mcp,code-quality,linting,python,code-analysis,cursor,ide
Classifier: Development Status :: 4 - Beta
Classifier: Intended Audience :: Developers
Classifier: License :: OSI Approved :: MIT License
Classifier: Programming Language :: Python :: 3
Classifier: Programming Language :: Python :: 3.8
Classifier: Programming Language :: Python :: 3.9
Classifier: Programming Language :: Python :: 3.10
Classifier: Programming Language :: Python :: 3.11
Classifier: Programming Language :: Python :: 3.12
Classifier: Topic :: Software Development :: Quality Assurance
Classifier: Topic :: Software Development :: Libraries :: Python Modules
Requires-Python: >=3.8
License-File: LICENSE
Requires-Dist: mcp>=0.9.0
Requires-Dist: pylint>=2.17.0
Requires-Dist: radon>=5.1.0
Requires-Dist: codespell>=2.2.0
Requires-Dist: coverage>=7.0.0
Requires-Dist: pyyaml>=6.0
Requires-Dist: click>=8.0.0
Requires-Dist: colorama>=0.4.6
Requires-Dist: tabulate>=0.9.0
Requires-Dist: jedi>=0.19.0
Requires-Dist: pycodestyle>=2.11.0
Requires-Dist: pydocstyle>=6.3.0
Requires-Dist: gitpython>=3.1.0
Provides-Extra: dev
Requires-Dist: pytest>=7.0.0; extra == "dev"
Requires-Dist: pytest-cov>=4.0.0; extra == "dev"
Requires-Dist: pytest-asyncio>=0.21.0; extra == "dev"
Requires-Dist: black>=23.0.0; extra == "dev"
Requires-Dist: mypy>=1.0.0; extra == "dev"
Requires-Dist: pre-commit>=3.0.0; extra == "dev"
Dynamic: license-file
